logninja_create_vm/__init__.py
logninja_create_vm/cli.py
logninja_create_vm/provision.py
logninja_create_vm-0.1.4.dev0.dist-info/licenses/LICENSE
logninja_create_vm-0.1.4.dev0.dist-info/METADATA
logninja_create_vm-0.1.4.dev0.dist-info/WHEEL
logninja_create_vm-0.1.4.dev0.dist-info/entry_points.txt
logninja_create_vm-0.1.4.dev0.dist-info/top_level.txt
logninja_create_vm-0.1.4.dev0.dist-info/RECORD
