Metadata-Version: 2.4
Name: logninja-create-vm
Version: 0.1.4.dev0
Summary: Interactive CLI tool for provisioning virtual machines using virt-install (LOGGIE infrastructure)
Home-page: https://github.com/loggie-eth/logninja-create-vm
Author: loggie.eth
Author-email: founder@loggie.ai
License: MIT
Classifier: Development Status :: 3 - Alpha
Classifier: Intended Audience :: System Administrators
Classifier: License :: OSI Approved :: MIT License
Classifier: Operating System :: POSIX :: Linux
Classifier: Programming Language :: Python :: 3
Classifier: Topic :: System :: Emulators
Classifier: Topic :: Utilities
Requires-Python: >=3.7
License-File: LICENSE
Dynamic: author
Dynamic: author-email
Dynamic: classifier
Dynamic: description
Dynamic: description-content-type
Dynamic: home-page
Dynamic: license
Dynamic: license-file
Dynamic: requires-python
Dynamic: summary
